tfq0tool/__init__.py
tfq0tool/__main__.py
tfq0tool/config.py
tfq0tool/extractors.py
tfq0tool/processor.py
tfq0tool/tfq0tool.py
tfq0tool/utils.py
tfq0tool-2.1.8.dist-info/licenses/LICENSE
tfq0tool-2.1.8.dist-info/METADATA
tfq0tool-2.1.8.dist-info/WHEEL
tfq0tool-2.1.8.dist-info/entry_points.txt
tfq0tool-2.1.8.dist-info/top_level.txt
tfq0tool-2.1.8.dist-info/RECORD
