Metadata-Version: 2.4
Name: tfq0tool
Version: 2.1.8
Summary: A powerful text extraction utility for multiple file formats, including PDFs, Word documents, spreadsheets, and code files.
Home-page: https://github.com/tfq0/tfq0tool
Author: Talal
Project-URL: Bug Reports, https://github.com/tfq0/TFQ0tool/issues
Project-URL: Source, https://github.com/tfq0/TFQ0tool
Keywords: text extraction pdf docx xlsx ocr
Classifier: Development Status :: 4 - Beta
Classifier: Intended Audience :: End Users/Desktop
Classifier: Topic :: Text Processing :: General
Classifier: Programming Language :: Python :: 3
Classifier: Programming Language :: Python :: 3.8
Classifier: Programming Language :: Python :: 3.9
Classifier: Programming Language :: Python :: 3.10
Classifier: Programming Language :: Python :: 3.11
Classifier: License :: OSI Approved :: MIT License
Classifier: Operating System :: OS Independent
Classifier: Environment :: Console
Requires-Python: >=3.8
License-File: LICENSE
Requires-Dist: PyPDF2>=3.0.0
Requires-Dist: python-docx>=0.8.11
Requires-Dist: pandas>=1.5.0
Requires-Dist: openpyxl>=3.1.0
Requires-Dist: pdfminer.six>=20221105
Requires-Dist: chardet>=5.0.0
Requires-Dist: tqdm>=4.65.0
Requires-Dist: pytesseract>=0.3.10
Requires-Dist: Pillow>=9.5.0
Requires-Dist: python-magic>=0.4.27
Requires-Dist: python-magic-bin>=0.4.14; sys_platform == "win32"
Dynamic: author
Dynamic: classifier
Dynamic: description
Dynamic: description-content-type
Dynamic: home-page
Dynamic: keywords
Dynamic: license-file
Dynamic: project-url
Dynamic: requires-dist
Dynamic: requires-python
Dynamic: summary
